README.md
setup.cfg
setup.py
python_requestr.egg-info/PKG-INFO
python_requestr.egg-info/SOURCES.txt
python_requestr.egg-info/dependency_links.txt
python_requestr.egg-info/requires.txt
python_requestr.egg-info/top_level.txt
requestr/__init__.py
requestr/api.py
requestr/futures_api.py
requestr/futures_session.py
requestr/sessions.py