Metadata-Version: 2.1
Name: python-requestr
Version: 0.13
Summary: requestr
Home-page: https://github.com/xjxckk/python-requestr/
Download-URL: https://github.com/xjxckk/python-requestr/archive/refs/tags/v0.1.tar.gz
